envass/__init__.py
envass/functions.py
envass/main.py
envass/methods.py
tests/__init__.py
tests/context.py
tests/test_main.py
envass-1.0.1.dist-info/METADATA
envass-1.0.1.dist-info/WHEEL
envass-1.0.1.dist-info/top_level.txt
envass-1.0.1.dist-info/RECORD
