Metadata-Version: 2.4
Name: envass
Version: 1.0.1
Summary: ENVASS ENVironmental data quality ASSurance.
Home-page: https://github.com/eawag-surface-waters-research/envass
Author: James Runnalls
Author-email: <james.runnalls@eawag.ch>
License: MIT
Keywords: python,ENVASS,quality assurance,environmental data
Requires-Dist: ipywidgets>=7.6.5
Requires-Dist: numpy>=1.19.5
Requires-Dist: pandas>=1.1.5
Requires-Dist: plotly>=5.6.0
Requires-Dist: scikit-learn>=0.24.2
Requires-Dist: scipy>=1.5.4
Dynamic: author
Dynamic: author-email
Dynamic: description
Dynamic: description-content-type
Dynamic: home-page
Dynamic: keywords
Dynamic: license
Dynamic: requires-dist
Dynamic: summary
